{
	"configurations" : 
	[
		{
			"directories" : 
			[
				{
					"build" : ".",
					"jsonFile" : "directory-.-Debug-d0094a50bb2071803777.json",
					"minimumCMakeVersion" : 
					{
						"string" : "3.22"
					},
					"projectIndex" : 0,
					"source" : ".",
					"targetIndexes" : 
					[
						0
					]
				}
			],
			"name" : "Debug",
			"projects" : 
			[
				{
					"directoryIndexes" : 
					[
						0
					],
					"name" : "refactroizacion_baremetal",
					"targetIndexes" : 
					[
						0
					]
				}
			],
			"targets" : 
			[
				{
					"directoryIndex" : 0,
					"id" : "refactroizacion_baremetal::@6890427a1f51a3e7e1df",
					"jsonFile" : "target-refactroizacion_baremetal-Debug-9a6e979c7ac4d8b2c1f5.json",
					"name" : "refactroizacion_baremetal",
					"projectIndex" : 0
				}
			]
		}
	],
	"kind" : "codemodel",
	"paths" : 
	{
		"build" : "C:/Users/juanv/Documents/projetc_estructuras/LIBRERIA_GPIO/build/debug",
		"source" : "C:/Users/juanv/Documents/projetc_estructuras/LIBRERIA_GPIO"
	},
	"version" : 
	{
		"major" : 2,
		"minor" : 6
	}
}
